odoo9_addon_purchase_order_line_sequence-9.0.1.0.1.99.dev6-py2.7-nspkg.pth
odoo9_addon_purchase_order_line_sequence-9.0.1.0.1.99.dev6.dist-info/METADATA
odoo9_addon_purchase_order_line_sequence-9.0.1.0.1.99.dev6.dist-info/RECORD
odoo9_addon_purchase_order_line_sequence-9.0.1.0.1.99.dev6.dist-info/WHEEL
odoo9_addon_purchase_order_line_sequence-9.0.1.0.1.99.dev6.dist-info/namespace_packages.txt
odoo9_addon_purchase_order_line_sequence-9.0.1.0.1.99.dev6.dist-info/top_level.txt
odoo_addons/purchase_order_line_sequence/README.rst
odoo_addons/purchase_order_line_sequence/__init__.py
odoo_addons/purchase_order_line_sequence/__openerp__.py
odoo_addons/purchase_order_line_sequence/i18n/fr.po
odoo_addons/purchase_order_line_sequence/i18n/purchase_order_line_sequence.pot
odoo_addons/purchase_order_line_sequence/models/__init__.py
odoo_addons/purchase_order_line_sequence/models/invoice.py
odoo_addons/purchase_order_line_sequence/models/purchase.py
odoo_addons/purchase_order_line_sequence/static/description/icon.png
odoo_addons/purchase_order_line_sequence/tests/__init__.py
odoo_addons/purchase_order_line_sequence/tests/test_po_lines_sequence.py
odoo_addons/purchase_order_line_sequence/views/purchase_view.xml
odoo_addons/purchase_order_line_sequence/views/report_purchaseorder.xml
odoo_addons/purchase_order_line_sequence/views/report_purchasequotation.xml
